xagg_no_xesmf_deps/__init__.py
xagg_no_xesmf_deps/_version.py
xagg_no_xesmf_deps/auxilary.py
xagg_no_xesmf_deps/classes.py
xagg_no_xesmf_deps/core.py
xagg_no_xesmf_deps/export.py
xagg_no_xesmf_deps/wrappers.py
xagg_no_xesmf_deps-0.3.0.4.dist-info/LICENSE
xagg_no_xesmf_deps-0.3.0.4.dist-info/METADATA
xagg_no_xesmf_deps-0.3.0.4.dist-info/WHEEL
xagg_no_xesmf_deps-0.3.0.4.dist-info/top_level.txt
xagg_no_xesmf_deps-0.3.0.4.dist-info/RECORD
