Metadata-Version: 2.1
Name: xagg-no-xesmf-deps
Version: 0.3.0.4
Summary: Aggregating raster data over polygons
Home-page: https://github.com/ks905383/xagg
Author: Kevin Schwarzwald
Author-email: kschwarzwald@iri.columbia.edu
License: GNU General Public License (GPL)
Classifier: Programming Language :: Python :: 3
Classifier: License :: OSI Approved :: GNU General Public License (GPL)
Classifier: Operating System :: OS Independent
Requires-Python: >=3.6
License-File: LICENSE
Requires-Dist: numpy
Requires-Dist: scipy
Requires-Dist: xarray
Requires-Dist: pandas
Requires-Dist: netcdf4
Requires-Dist: geopandas
Requires-Dist: shapely
Requires-Dist: tables
Requires-Dist: cf-xarray (>=0.5.1)
